MibiPlot/__init__.py
MibiPlot/index.py
MibiPlot-0.1.post2.dist-info/LICENSE
MibiPlot-0.1.post2.dist-info/METADATA
MibiPlot-0.1.post2.dist-info/WHEEL
MibiPlot-0.1.post2.dist-info/top_level.txt
MibiPlot-0.1.post2.dist-info/RECORD
