Metadata-Version: 2.1
Name: MibiPlot
Version: 0.1.post2
Summary: Make plots in a console
Home-page: https://github.com/mibi88/MibiPlot
Author: mibi88
Author-email: mbcontact50@gmail.com
License: UNKNOWN
Project-URL: Bug Tracker, https://github.com/mibi88/MibiPlot/issues
Platform: UNKNOWN
Classifier: Programming Language :: Python :: 2
Classifier: License :: OSI Approved :: GNU General Public License v2 (GPLv2)
Classifier: Operating System :: OS Independent
Requires-Python: >=2.7
License-File: LICENSE
